hammingdist.cpython-311-darwin.so
hammingdist-1.4.0.dist-info/RECORD
hammingdist-1.4.0.dist-info/WHEEL
hammingdist-1.4.0.dist-info/METADATA
hammingdist-1.4.0.dist-info/licenses/LICENSE.md
